{
    "version": "0.48.7",
    "description": "An Open Source Minecraft Launcher with Modern UX.",
    "homepage": "https://xmcl.app/",
    "license": "MIT",
    "architecture": {
        "64bit": {
            "url": "https://github.com/Voxelum/x-minecraft-launcher/releases/download/v0.48.7/xmcl-0.48.7-win32-x64.zip",
            "hash": "c42108d060c02f74d7275658e233163e4d7840161e119948caf8c0b1e9921add"
        },
        "32bit": {
            "url": "https://github.com/Voxelum/x-minecraft-launcher/releases/download/v0.48.7/xmcl-0.48.7-win32-ia32.zip",
            "hash": "ed01baebe2c0eca61b9e612e3b8274b489b0dfbdc44f3c9dbda16a8cfafe50f4"
        }
    },
    "bin": "xmcl.exe",
    "shortcuts": [
        [
            "xmcl.exe",
            "XMCL"
        ]
    ],
    "checkver": {
        "github": "https://github.com/Voxelum/x-minecraft-launcher"
    },
    "autoupdate": {
        "architecture": {
            "64bit": {
                "url": "https://github.com/Voxelum/x-minecraft-launcher/releases/download/v$version/xmcl-$version-win32-x64.zip"
            },
            "32bit": {
                "url": "https://github.com/Voxelum/x-minecraft-launcher/releases/download/v$version/xmcl-$version-win32-ia32.zip"
            }
        }
    }
}
